Workbook
Name NativeTimeline_Customer_Since: #N/A
Name NativeTimeline_Date: #N/A
Name Slicer_Category: #N/A
Name Slicer_Region: #N/A

Sheet Project Instructions
A1: PR. Final Project - "Data Intelligence Dashboard"
A2: Dataset: Use the 'Final Project Dataset' sheet containing 200+ records of customer transactions. Objective: Create a full-fledged analysis and reporting solution using Excel to analyze customer transactions, find insights, and build visualizations and dashboards. Key Topics to Implement: - Date & Time Functions: TODAY, NOW, DATEDIF, EOMONTH - FILTER Function for multi-value returns - Conditional Formatting with Icons/Arrows - Create Timestamp (using NOW and iterative calculations) - WHAT-IF Analysis: Scenario Manager, Goal Seek - Linear Regression using Data Analysis Toolpak - Data Analysis & Storytelling from the dataset - Use GroupBy concepts to find High-Value Customers using formulas - Create Dashboard using: - Pivot Tables - Pivot Charts (Bar, Line, Pie) - Slicers and Timelines - KPI Indicators with Conditional Formatting - Find most frequently purchased product or repeating names using formulas - Compare two lists and extract matching names in a new column - Create Abbreviations using TEXT functions - Build a final report with insights and storytelling Deliverable: - Well-structured workbook with multiple sheets (Raw Data, Analysis, Visualizations, Dashboard) - Summary Insights with key metrics: Total Revenue, Top Customers, Most Sold Products, Regional Sales - Use of all required formulas and functions as listed above

Sheet Final Project Dataset
A1: Transaction_ID | B1: Date | C1: Customer_ID | D1: Customer_Name | E1: Product_ID | F1: Product_Name | G1: Category | H1: Quantity | I1: Unit_Price | J1: Payment_Method | K1: Region | L1: Customer_Segment | M1: Customer_Since | N1: Total_Amount
A2: TRX0155 | B2: 45393 | C2: CUST023 | D2: Paul Baker | E2: P009 | F2: Monitor | G2: Electronics | H2: 3 | I2: 249.99 | J2: Cash | K2: Central | L2: Basic | M2: 44425 | N2: 749.97
A3: TRX0023 | B3: 45396 | C3: CUST013 | D3: Joseph Jackson | E3: P009 | F3: Monitor | G3: Electronics | H3: 3 | I3: 249.99 | J3: Credit Card | K3: Central | L3: Premium | M3: 44575 | N3: 749.97
A4: TRX0139 | B4: 45399 | C4: CUST021 | D4: Kevin Scott | E4: P005 | F4: Blender | G4: Appliances | H4: 3 | I4: 59.99 | J4: PayPal | K4: South | L4: Standard | M4: 45262 | N4: 179.97
A5: TRX0043 | B5: 45400 | C5: CUST046 | D5: Kathleen Bennett | E5: P005 | F5: Blender | G5: Appliances | H5: 3 | I5: 59.99 | J5: Cash | K5: North | L5: Premium | M5: 45114 | N5: 179.97
A6: TRX0212 | B6: 45400 | C6: CUST003 | D6: Michael Brown | E6: P008 | F6: Bookshelf | G6: Furniture | H6: 5 | I6: 149.99 | J6: Credit Card | K6: North | L6: Premium | M6: 45295 | N6: 749.95
A7: TRX0092 | B7: 45403 | C7: CUST024 | D7: Dorothy Nelson | E7: P005 | F7: Blender | G7: Appliances | H7: 2 | I7: 59.99 | J7: Cash | K7: West | L7: Standard | M7: 44746 | N7: 119.98
A8: TRX0193 | B8: 45403 | C8: CUST024 | D8: Dorothy Nelson | E8: P003 | F8: Headphones | G8: Electronics | H8: 5 | I8: 149.99 | J8: Credit Card | K8: Central | L8: Standard | M8: 44418 | N8: 749.95
A9: TRX0240 | B9: 45403 | C9: CUST017 | D9: Charles Allen | E9: P005 | F9: Blender | G9: Appliances | H9: 3 | I9: 59.99 | J9: Debit Card | K9: South | L9: Basic | M9: 45007 | N9: 179.97
A10: TRX0135 | B10: 45405 | C10: CUST009 | D10: Robert Thomas | E10: P001 | F10: Laptop | G10: Electronics | H10: 3 | I10: 899.99 | J10: PayPal | K10: East | L10: Standard | M10: 45299 | N10: 2699.97
A11: TRX0185 | B11: 45408 | C11: CUST026 | D11: Karen Hill | E11: P005 | F11: Blender | G11: Appliances | H11: 3 | I11: 59.99 | J11: Cash | K11: West | L11: Premium | M11: 45207 | N11: 179.97
A12: TRX0138 | B12: 45408 | C12: CUST022 | D12: Susan Green | E12: P008 | F12: Bookshelf | G12: Furniture | H12: 1 | I12: 149.99 | J12: Credit Card | K12: West | L12: Standard | M12: 45103 | N12: 149.99
A13: TRX0209 | B13: 45408 | C13: CUST046 | D13: Kathleen Bennett | E13: P008 | F13: Bookshelf | G13: Furniture | H13: 5 | I13: 149.99 | J13: Debit Card | K13: North | L13: Basic | M13: 44830 | N13: 749.95
... A251: TRX0064 | B251: 45758 | C251: CUST031 | D251: Steven Turner | E251: P010 | F251: Keyboard | G251: Electronics | H251: 3 | I251: 89.99 | J251: Debit Card | K251: North | L251: Premium | M251: 44878 | N251: 269.97

Sheet Date
A1: Date | B1: Customer_Since | C1: TODAY | D1: NOW | E1: DATEDIF | F1: EOMONTH
A2: 45393 | B2: 44425 | C2: =TODAY() -> 46312 | D2: =NOW() -> 46312.742 | E2: =DATEDIF(B2, A2, "d") -> 968 | F2: =EOMONTH(A2,1) -> 45443
A3: 45396 | B3: 44575 | C3: =TODAY() -> 46312 | D3: =NOW() -> 46312.742 | E3: =DATEDIF(B3, A3, "d") -> 821 | F3: =EOMONTH(A3,1) -> 45443
A4: 45399 | B4: 45262 | C4: =TODAY() -> 46312 | D4: =NOW() -> 46312.742 | E4: =DATEDIF(B4, A4, "d") -> 137 | F4: =EOMONTH(A4,1) -> 45443
A5: 45400 | B5: 45114 | C5: =TODAY() -> 46312 | D5: =NOW() -> 46312.742 | E5: =DATEDIF(B5, A5, "d") -> 286 | F5: =EOMONTH(A5,1) -> 45443
A6: 45400 | B6: 45295 | C6: =TODAY() -> 46312 | D6: =NOW() -> 46312.742 | E6: =DATEDIF(B6, A6, "d") -> 105 | F6: =EOMONTH(A6,1) -> 45443
A7: 45403 | B7: 44746 | C7: =TODAY() -> 46312 | D7: =NOW() -> 46312.742 | E7: =DATEDIF(B7, A7, "d") -> 657 | F7: =EOMONTH(A7,1) -> 45443
A8: 45403 | B8: 44418 | C8: =TODAY() -> 46312 | D8: =NOW() -> 46312.742 | E8: =DATEDIF(B8, A8, "d") -> 985 | F8: =EOMONTH(A8,1) -> 45443
A9: 45403 | B9: 45007 | C9: =TODAY() -> 46312 | D9: =NOW() -> 46312.742 | E9: =DATEDIF(B9, A9, "d") -> 396 | F9: =EOMONTH(A9,1) -> 45443
A10: 45405 | B10: 45299 | C10: =TODAY() -> 46312 | D10: =NOW() -> 46312.742 | E10: =DATEDIF(B10, A10, "d") -> 106 | F10: =EOMONTH(A10,1) -> 45443
A11: 45408 | B11: 45207 | C11: =TODAY() -> 46312 | D11: =NOW() -> 46312.742 | E11: =DATEDIF(B11, A11, "d") -> 201 | F11: =EOMONTH(A11,1) -> 45443
A12: 45408 | B12: 45103 | C12: =TODAY() -> 46312 | D12: =NOW() -> 46312.742 | E12: =DATEDIF(B12, A12, "d") -> 305 | F12: =EOMONTH(A12,1) -> 45443
A13: 45408 | B13: 44830 | C13: =TODAY() -> 46312 | D13: =NOW() -> 46312.742 | E13: =DATEDIF(B13, A13, "d") -> 578 | F13: =EOMONTH(A13,1) -> 45443
... A251: 45758 | B251: 44878 | C251: =TODAY() -> 46312 | D251: =NOW() -> 46312.742 | E251: =DATEDIF(B251, A251, "d") -> 880 | F251: =EOMONTH(A251,1) -> 45808

Sheet FILTER
A1: UNIQUE | B1: COUNTIF | C1: SUMIF | D1: IF | E1: FILTER
A2: {=_xlfn.UNIQUE('Final Project Dataset'!D2:D251)} -> Paul Baker | B2: =COUNTIF('Final Project Dataset'!D:D,FILTER!A2) -> 8 | C2: =SUMIF('Final Project Dataset'!D:D,FILTER!A2,'Final Project Dataset'!N:N) -> 8309.74 | D2: =IF('Final Project Dataset'!N2>=1000, "High Value", IF('Final Project Dataset'!N2>=500, "Medium Value", "Low Value")) -> Medium Value | E2: {=_xlfn._xlws.FILTER('Final Project Dataset'!A2:N251, ('Final Project Dataset'!G2:G251="Electronics") * ('Final Project Dataset'!K2:K251="East"), "No Records Found")} -> TRX0135 | F2: 45405 | G2: CUST009 | H2: Robert Thomas | I2: P001 | J2: Laptop | K2: Electronics | L2: 3 | M2: 899.99 | N2: PayPal | O2: East | P2: Standard | Q2: 45299 | R2: 2699.97
A3: Joseph Jackson | B3: =COUNTIF('Final Project Dataset'!D:D,FILTER!A3) -> 5 | C3: =SUMIF('Final Project Dataset'!D:D,FILTER!A3,'Final Project Dataset'!N:N) -> 6949.84 | D3: =IF('Final Project Dataset'!N3>=1000, "High Value", IF('Final Project Dataset'!N3>=500, "Medium Value", "Low Value")) -> Medium Value | E3: TRX0239 | F3: 45413 | G3: CUST012 | H3: Patricia Moore | I3: P002 | J3: Smartphone | K3: Electronics | L3: 4 | M3: 699.99 | N3: Cash | O3: East | P3: Standard | Q3: 44409 | R3: 2799.96
A4: Kevin Scott | B4: =COUNTIF('Final Project Dataset'!D:D,FILTER!A4) -> 6 | C4: =SUMIF('Final Project Dataset'!D:D,FILTER!A4,'Final Project Dataset'!N:N) -> 3259.87 | D4: =IF('Final Project Dataset'!N4>=1000, "High Value", IF('Final Project Dataset'!N4>=500, "Medium Value", "Low Value")) -> Low Value | E4: TRX0208 | F4: 45446 | G4: CUST004 | H4: Sarah Davis | I4: P010 | J4: Keyboard | K4: Electronics | L4: 5 | M4: 89.99 | N4: Credit Card | O4: East | P4: Standard | Q4: 44587 | R4: 449.95
A5: Kathleen Bennett | B5: =COUNTIF('Final Project Dataset'!D:D,FILTER!A5) -> 6 | C5: =SUMIF('Final Project Dataset'!D:D,FILTER!A5,'Final Project Dataset'!N:N) -> 4309.81 | D5: =IF('Final Project Dataset'!N5>=1000, "High Value", IF('Final Project Dataset'!N5>=500, "Medium Value", "Low Value")) -> Low Value | E5: TRX0234 | F5: 45449 | G5: CUST013 | H5: Joseph Jackson | I5: P009 | J5: Monitor | K5: Electronics | L5: 5 | M5: 249.99 | N5: Credit Card | O5: East | P5: Standard | Q5: 44707 | R5: 1249.95
A6: Michael Brown | B6: =COUNTIF('Final Project Dataset'!D:D,FILTER!A6) -> 9 | C6: =SUMIF('Final Project Dataset'!D:D,FILTER!A6,'Final Project Dataset'!N:N) -> 6169.74 | D6: =IF('Final Project Dataset'!N6>=1000, "High Value", IF('Final Project Dataset'!N6>=500, "Medium Value", "Low Value")) -> Medium Value | E6: TRX0044 | F6: 45459 | G6: CUST029 | H6: Edward Mitchell | I6: P001 | J6: Laptop | K6: Electronics | L6: 5 | M6: 899.99 | N6: PayPal | O6: East | P6: Premium | Q6: 45278 | R6: 4499.95
A7: Dorothy Nelson | B7: =COUNTIF('Final Project Dataset'!D:D,FILTER!A7) -> 6 | C7: =SUMIF('Final Project Dataset'!D:D,FILTER!A7,'Final Project Dataset'!N:N) -> 8269.79 | D7: =IF('Final Project Dataset'!N7>=1000, "High Value", IF('Final Project Dataset'!N7>=500, "Medium Value", "Low Value")) -> Low Value | E7: TRX0184 | F7: 45471 | G7: CUST046 | H7: Kathleen Bennett | I7: P002 | J7: Smartphone | K7: Electronics | L7: 3 | M7: 699.99 | N7: Credit Card | O7: East | P7: Premium | Q7: 45102 | R7: 2099.97
A8: Charles Allen | B8: =COUNTIF('Final Project Dataset'!D:D,FILTER!A8) -> 9 | C8: =SUMIF('Final Project Dataset'!D:D,FILTER!A8,'Final Project Dataset'!N:N) -> 5089.73 | D8: =IF('Final Project Dataset'!N8>=1000, "High Value", IF('Final Project Dataset'!N8>=500, "Medium Value", "Low Value")) -> Medium Value | E8: TRX0104 | F8: 45471 | G8: CUST012 | H8: Patricia Moore | I8: P001 | J8: Laptop | K8: Electronics | L8: 4 | M8: 899.99 | N8: Credit Card | O8: East | P8: Premium | Q8: 44993 | R8: 3599.96
A9: Robert Thomas | B9: =COUNTIF('Final Project Dataset'!D:D,FILTER!A9) -> 5 | C9: =SUMIF('Final Project Dataset'!D:D,FILTER!A9,'Final Project Dataset'!N:N) -> 3509.9 | D9: =IF('Final Project Dataset'!N9>=1000, "High Value", IF('Final Project Dataset'!N9>=500, "Medium Value", "Low Value")) -> Low Value | E9: TRX0113 | F9: 45481 | G9: CUST003 | H9: Michael Brown | I9: P002 | J9: Smartphone | K9: Electronics | L9: 2 | M9: 699.99 | N9: PayPal | O9: East | P9: Premium | Q9: 45389 | R9: 1399.98
A10: Karen Hill | B10: =COUNTIF('Final Project Dataset'!D:D,FILTER!A10) -> 8 | C10: =SUMIF('Final Project Dataset'!D:D,FILTER!A10,'Final Project Dataset'!N:N) -> 8009.77 | D10: =IF('Final Project Dataset'!N10>=1000, "High Value", IF('Final Project Dataset'!N10>=500, "Medium Value", "Low Value")) -> High Value | E10: TRX0075 | F10: 45517 | G10: CUST020 | H10: Margaret Wright | I10: P009 | J10: Monitor | K10: Electronics | L10: 5 | M10: 249.99 | N10: PayPal | O10: East | P10: Premium | Q10: 44782 | R10: 1249.95
A11: Susan Green | B11: =COUNTIF('Final Project Dataset'!D:D,FILTER!A11) -> 4 | C11: =SUMIF('Final Project Dataset'!D:D,FILTER!A11,'Final Project Dataset'!N:N) -> 1979.89 | D11: =IF('Final Project Dataset'!N11>=1000, "High Value", IF('Final Project Dataset'!N11>=500, "Medium Value", "Low Value")) -> Low Value | E11: TRX0140 | F11: 45522 | G11: CUST025 | H11: Mark Carter | I11: P010 | J11: Keyboard | K11: Electronics | L11: 2 | M11: 89.99 | N11: Cash | O11: East | P11: Premium | Q11: 44972 | R11: 179.98
A12: Peter Richardson | B12: =COUNTIF('Final Project Dataset'!D:D,FILTER!A12) -> 5 | C12: =SUMIF('Final Project Dataset'!D:D,FILTER!A12,'Final Project Dataset'!N:N) -> 5949.85 | D12: =IF('Final Project Dataset'!N12>=1000, "High Value", IF('Final Project Dataset'!N12>=500, "Medium Value", "Low Value")) -> Low Value | E12: TRX0132 | F12: 45523 | G12: CUST047 | H12: Gerald Murphy | I12: P001 | J12: Laptop | K12: Electronics | L12: 5 | M12: 899.99 | N12: Debit Card | O12: East | P12: Basic | Q12: 44526 | R12: 4499.95
A13: Dennis Gray | B13: =COUNTIF('Final Project Dataset'!D:D,FILTER!A13) -> 2 | C13: =SUMIF('Final Project Dataset'!D:D,FILTER!A13,'Final Project Dataset'!N:N) -> 479.92 | D13: =IF('Final Project Dataset'!N13>=1000, "High Value", IF('Final Project Dataset'!N13>=500, "Medium Value", "Low Value")) -> Medium Value | E13: TRX0031 | F13: 45523 | G13: CUST036 | H13: Nancy Collins | I13: P003 | J13: Headphones | K13: Electronics | L13: 3 | M13: 149.99 | N13: PayPal | O13: East | P13: Basic | Q13: 44574 | R13: 449.97
A14: Michelle Rogers | B14: =COUNTIF('Final Project Dataset'!D:D,FILTER!A14) -> 2 | C14: =SUMIF('Final Project Dataset'!D:D,FILTER!A14,'Final Project Dataset'!N:N) -> 4199.94 | D14: =IF('Final Project Dataset'!N14>=1000, "High Value", IF('Final Project Dataset'!N14>=500, "Medium Value", "Low Value")) -> Low Value | E14: TRX0077 | F14: 45554 | G14: CUST019 | H14: Daniel King | I14: P010 | J14: Keyboard | K14: Electronics | L14: 5 | M14: 89.99 | N14: Credit Card | O14: East | P14: Premium | Q14: 44446 | R14: 449.95
... A28: Steven Turner | B28: =COUNTIF('Final Project Dataset'!D:D,FILTER!A28) -> 6 | C28: =SUMIF('Final Project Dataset'!D:D,FILTER!A28,'Final Project Dataset'!N:N) -> 2649.83 | D28: =IF('Final Project Dataset'!N28>=1000, "High Value", IF('Final Project Dataset'!N28>=500, "Medium Value", "Low Value")) -> Low Value | E28: TRX0103 | F28: 45758 | G28: CUST039 | H28: Lawrence Reed | I28: P010 | J28: Keyboard | K28: Electronics | L28: 2 | M28: 89.99 | N28: Debit Card | O28: East | P28: Basic | Q28: 45088 | R28: 179.98
A29: Jennifer Taylor | B29: =COUNTIF('Final Project Dataset'!D:D,FILTER!A29) -> 4 | C29: =SUMIF('Final Project Dataset'!D:D,FILTER!A29,'Final Project Dataset'!N:N) -> 4739.85 | D29: =IF('Final Project Dataset'!N29>=1000, "High Value", IF('Final Project Dataset'!N29>=500, "Medium Value", "Low Value")) -> Low Value
A30: Harry Morgan | B30: =COUNTIF('Final Project Dataset'!D:D,FILTER!A30) -> 4 | C30: =SUMIF('Final Project Dataset'!D:D,FILTER!A30,'Final Project Dataset'!N:N) -> 5519.89 | D30: =IF('Final Project Dataset'!N30>=1000, "High Value", IF('Final Project Dataset'!N30>=500, "Medium Value", "Low Value")) -> Low Value
A31: Daniel King | B31: =COUNTIF('Final Project Dataset'!D:D,FILTER!A31) -> 7 | C31: =SUMIF('Final Project Dataset'!D:D,FILTER!A31,'Final Project Dataset'!N:N) -> 7309.8 | D31: =IF('Final Project Dataset'!N31>=1000, "High Value", IF('Final Project Dataset'!N31>=500, "Medium Value", "Low Value")) -> Low Value
A32: Sharon Butler | B32: =COUNTIF('Final Project Dataset'!D:D,FILTER!A32) -> 6 | C32: =SUMIF('Final Project Dataset'!D:D,FILTER!A32,'Final Project Dataset'!N:N) -> 5619.87 | D32: =IF('Final Project Dataset'!N32>=1000, "High Value", IF('Final Project Dataset'!N32>=500, "Medium Value", "Low Value")) -> Medium Value
A33: Sarah Davis | B33: =COUNTIF('Final Project Dataset'!D:D,FILTER!A33) -> 5 | C33: =SUMIF('Final Project Dataset'!D:D,FILTER!A33,'Final Project Dataset'!N:N) -> 5499.81 | D33: =IF('Final Project Dataset'!N33>=1000, "High Value", IF('Final Project Dataset'!N33>=500, "Medium Value", "Low Value")) -> Low Value
A34: Betty Campbell | B34: =COUNTIF('Final Project Dataset'!D:D,FILTER!A34) -> 5 | C34: =SUMIF('Final Project Dataset'!D:D,FILTER!A34,'Final Project Dataset'!N:N) -> 5649.84 | D34: =IF('Final Project Dataset'!N34>=1000, "High Value", IF('Final Project Dataset'!N34>=500, "Medium Value", "Low Value")) -> Low Value
A35: Julie Foster | B35: =COUNTIF('Final Project Dataset'!D:D,FILTER!A35) -> 1 | C35: =SUMIF('Final Project Dataset'!D:D,FILTER!A35,'Final Project Dataset'!N:N) -> 239.96 | D35: =IF('Final Project Dataset'!N35>=1000, "High Value", IF('Final Project Dataset'!N35>=500, "Medium Value", "Low Value")) -> Medium Value
A36: Raymond Ross | B36: =COUNTIF('Final Project Dataset'!D:D,FILTER!A36) -> 4 | C36: =SUMIF('Final Project Dataset'!D:D,FILTER!A36,'Final Project Dataset'!N:N) -> 3669.85 | D36: =IF('Final Project Dataset'!N36>=1000, "High Value", IF('Final Project Dataset'!N36>=500, "Medium Value", "Low Value")) -> Medium Value
A37: David Martinez | B37: =COUNTIF('Final Project Dataset'!D:D,FILTER!A37) -> 6 | C37: =SUMIF('Final Project Dataset'!D:D,FILTER!A37,'Final Project Dataset'!N:N) -> 1809.84 | D37: =IF('Final Project Dataset'!N37>=1000, "High Value", IF('Final Project Dataset'!N37>=500, "Medium Value", "Low Value")) -> Low Value
A38: Margaret Wright | B38: =COUNTIF('Final Project Dataset'!D:D,FILTER!A38) -> 4 | C38: =SUMIF('Final Project Dataset'!D:D,FILTER!A38,'Final Project Dataset'!N:N) -> 2099.88 | D38: =IF('Final Project Dataset'!N38>=1000, "High Value", IF('Final Project Dataset'!N38>=500, "Medium Value", "Low Value")) -> Medium Value
A39: Frank Torres | B39: =COUNTIF('Final Project Dataset'!D:D,FILTER!A39) -> 5 | C39: =SUMIF('Final Project Dataset'!D:D,FILTER!A39,'Final Project Dataset'!N:N) -> 1479.91 | D39: =IF('Final Project Dataset'!N39>=1000, "High Value", IF('Final Project Dataset'!N39>=500, "Medium Value", "Low Value")) -> High Value
A40: Gerald Murphy | B40: =COUNTIF('Final Project Dataset'!D:D,FILTER!A40) -> 4 | C40: =SUMIF('Final Project Dataset'!D:D,FILTER!A40,'Final Project Dataset'!N:N) -> 6379.87 | D40: =IF('Final Project Dataset'!N40>=1000, "High Value", IF('Final Project Dataset'!N40>=500, "Medium Value", "Low Value")) -> Low Value
... A51: John Smith | B51: =COUNTIF('Final Project Dataset'!D:D,FILTER!A51) -> 1 | C51: =SUMIF('Final Project Dataset'!D:D,FILTER!A51,'Final Project Dataset'!N:N) -> 599.96 | D51: =IF('Final Project Dataset'!N51>=1000, "High Value", IF('Final Project Dataset'!N51>=500, "Medium Value", "Low Value")) -> High Value

Sheet Pivot
A3: Category | B3: Region | C3: Product_Name | D3: Date | E3: Sum of Total_Amount
A4: Furniture | B4: Central | C4: Desk | D4: 45501 | E4: 899.97
A5: Furniture | B5: Central | C5: Desk | D5: 45547 | E5: 899.97
A6: Furniture | B6: Central | C6: Desk | D6: 45563 | E6: 599.98
A7: Furniture | B7: Central | C7: Desk | D7: 45566 | E7: 1199.96
A8: Furniture | B8: Central | C8: Desk | D8: 45576 | E8: 899.97
A9: Furniture | B9: Central | C9: Desk | D9: 45673 | E9: 1499.95
A10: Grand Total | E10: 5999.8
A12: Sum of Total_Amount | B12: Column Labels
A13: Row Labels | B13: Basic | C13: Premium | D13: Standard | E13: Grand Total
A14: Central | B14: 16339.4 | C14: 15479.35 | D14: 9469.59 | E14: 41288.34
A15: East | B15: 9319.68 | C15: 26009.43 | D15: 23959.28 | E15: 59288.39
A16: North | B16: 14799.51 | C16: 26569.11 | D16: 9439.69 | E16: 50808.31
A17: South | B17: 10419.54 | C17: 6499.74 | D17: 19479.47 | E17: 36398.75
A18: West | B18: 11299.68 | C18: 10099.49 | D18: 20009.51 | E18: 41408.68
A19: Grand Total | B19: 62177.81 | C19: 84657.12 | D19: 82357.54 | E19: 229192.47

Sheet Charts

Sheet KPI
A2: Total Revenue | B2: Total Transactions | C2: Total Units Sold | D2: Average Transaction Value
A3: =SUM('Final Project Dataset'!N:N) -> 229192.47 | B3: =COUNTA('Final Project Dataset'!A2:A251) -> 250 | C3: =SUM('Final Project Dataset'!H2:H251) -> 753 | D3: =AVERAGE('Final Project Dataset'!N2:N251) -> 916.76988
A5: Total_Amount
A6: 749.97
A7: 749.97
A8: 179.97
A9: 179.97
A10: 749.95
A11: 119.98
A12: 749.95
A13: 179.97
A14: 2699.97
A15: 179.97
A16: 149.99
A17: 749.95
... A255: 269.97

Sheet  WHAT-IF Analysis
A1: TOTAL SALES
A2: =SUM('Final Project Dataset'!N:N) -> 229192.47 | B2: 1.1258966e+11
A4: 1.15
A6: LINEAR Regression
A7: SUMMARY OUTPUT
A9: Regression Statistics
A10: Multiple R | B10: 0.83544893
A11: R Square | B11: 0.69797492
A12: Adjusted R Square | B12: 0.69675708
A13: Standard Error | B13: 568.54608
A14: Observations | B14: 250
A16: ANOVA
B17: df | C17: SS | D17: MS | E17: F | F17: Significance F
A18: Regression | B18: 1 | C18: 1.8525922e+08 | D18: 1.8525922e+08 | E18: 573.12386 | F18: 2.0274088e-66
A19: Residual | B19: 248 | C19: 80164673 | D19: 323244.65
A20: Total | B20: 249 | C20: 2.6542389e+08
B22: Coefficients | C22: Standard Error | D22: t Stat | E22: P-value | F22: Lower 95% | G22: Upper 95% | H22: Lower 95.0% | I22: Upper 95.0%
A23: Intercept | B23: -14.342533 | C23: 52.968753 | D23: -0.27077347 | E23: 0.78679049 | F23: -118.6685 | G23: 89.983434 | H23: -118.6685 | I23: 89.983434
A24: X Variable 1 | B24: 3.1385459 | C24: 0.13110047 | D24: 23.940005 | E24: 2.0274088e-66 | F24: 2.8803336 | G24: 3.3967582 | H24: 2.8803336 | I24: 3.3967582
